{
    "$schema": "https://schema.management.azure.com/schemas/2015-01-01/deploymentParameters.json#",
    "contentVersion": "1.0.0.0",
    "parameters": {
        "location": {
            "value": "australiasoutheast"
        },
        "virtualMachineName": {
            "value": "PG-VM-AUTO-1"
        },
        "virtualMachineSize": {
            "value": "Standard_B1s"
        },
        "adminUsername": {
            "value": "admin-azure"
        },
        "virtualNetworkName": {
            "value": "PG-VNET"
        },
        "networkInterfaceName": {
            "value": "pg-vm-auto-1-NIC"
        },
        "adminPassword": {
            "value": "T1meP@$$4preet0mg0swam1"
        },
        "diagnosticsStorageAccountName": {
            "value": "azstoragestooti"
        },
        "diagnosticsStorageAccountId": {
            "value": "/subscriptions/c9cca591-73f9-4a5b-8447-2d76317cc3e8/resourceGroups/AZ_RG_STORAGE/providers/Microsoft.Storage/storageAccounts/azstoragestooti"
        },
        "subnetName": {
            "value": "VM-SUBNET"
        }
    }
}